README.rst
setup.py
amount_in_words/__init__.py
amount_in_words/amount.py
amount_in_words/tests.py
amount_in_words.egg-info/PKG-INFO
amount_in_words.egg-info/SOURCES.txt
amount_in_words.egg-info/dependency_links.txt
amount_in_words.egg-info/not-zip-safe
amount_in_words.egg-info/pbr.json
amount_in_words.egg-info/top_level.txt