Metadata-Version: 1.1
Name: amount-in-words
Version: 0.1.0
Summary: Convert amount to words (Polish translation).
Home-page: https://github.com/bogdal/amount-in-words
Author: Adam Bogdal
Author-email: adam@bogdal.pl
License: UNKNOWN
Download-URL: https://github.com/bogdal/amount-in-words/zipball/master
Platform: UNKNOWN
Classifier: Development Status :: 5 - Production/Stable
Classifier: Environment :: Console
Classifier: Intended Audience :: Developers
Classifier: License :: OSI Approved :: BSD License
Classifier: Operating System :: OS Independent
Classifier: Programming Language :: Python
Classifier: Topic :: Software Development :: Libraries :: Python Modules
Classifier: Topic :: Utilities
